tts_webui_extension/chatterbox/InterruptionFlag.py
tts_webui_extension/chatterbox/SUPPORTED_LANGUAGES.py
tts_webui_extension/chatterbox/__init__.py
tts_webui_extension/chatterbox/api.py
tts_webui_extension/chatterbox/decorator_convert_audio_output_generator.py
tts_webui_extension/chatterbox/demo.py
tts_webui_extension/chatterbox/gradio_app.py
tts_webui_extension/chatterbox/main.py
tts_webui_extension/chatterbox/memory.py
tts_webui_extension_chatterbox-4.2.2.dist-info/licenses/LICENSE
tts_webui_extension_chatterbox-4.2.2.dist-info/METADATA
tts_webui_extension_chatterbox-4.2.2.dist-info/WHEEL
tts_webui_extension_chatterbox-4.2.2.dist-info/top_level.txt
tts_webui_extension_chatterbox-4.2.2.dist-info/RECORD
