Metadata-Version: 2.4
Name: tts_webui_extension.chatterbox
Version: 4.2.2
Summary: A template extension for TTS Generation WebUI
Author: rsxdalv
Project-URL: Homepage, https://github.com/rsxdalv/tts_webui_extension.chatterbox
Classifier: Programming Language :: Python :: 3
Classifier: License :: OSI Approved :: MIT License
Classifier: Operating System :: OS Independent
Requires-Python: >=3.7
License-File: LICENSE
Requires-Dist: tts-webui.chatterbox-tts>=0.4.4
Dynamic: license-file
